nobrainer/__init__.py
nobrainer/_version.py
nobrainer/bayesian_utils.py
nobrainer/dataset.py
nobrainer/intensity_transforms.py
nobrainer/io.py
nobrainer/losses.py
nobrainer/metrics.py
nobrainer/prediction.py
nobrainer/spatial_transforms.py
nobrainer/tfrecord.py
nobrainer/training.py
nobrainer/transform.py
nobrainer/utils.py
nobrainer/validation.py
nobrainer/volume.py
nobrainer/cli/__init__.py
nobrainer/cli/main.py
nobrainer/cli/tests/__init__.py
nobrainer/cli/tests/main_test.py
nobrainer/distributed_learning/dwc.py
nobrainer/layers/Conv_v.py
nobrainer/layers/InstanceNorm.py
nobrainer/layers/__init__.py
nobrainer/layers/dropout.py
nobrainer/layers/groupnorm.py
nobrainer/layers/max_pool4d.py
nobrainer/layers/padding.py
nobrainer/layers/tests/__init__.py
nobrainer/layers/tests/dropout_test.py
nobrainer/layers/tests/layers_test.py
nobrainer/models/__init__.py
nobrainer/models/attention_unet.py
nobrainer/models/attention_unet_with_inception.py
nobrainer/models/autoencoder.py
nobrainer/models/bayesian_meshnet.py
nobrainer/models/bayesian_vnet.py
nobrainer/models/bayesian_vnet_semi.py
nobrainer/models/brainsiam.py
nobrainer/models/dcgan.py
nobrainer/models/highresnet.py
nobrainer/models/meshnet.py
nobrainer/models/progressiveae.py
nobrainer/models/progressivegan.py
nobrainer/models/unet.py
nobrainer/models/unet_lstm.py
nobrainer/models/unetr.py
nobrainer/models/vnet.py
nobrainer/models/vox2vox.py
nobrainer/models/tests/__init__.py
nobrainer/models/tests/models_test.py
nobrainer/processing/__init__.py
nobrainer/processing/base.py
nobrainer/processing/checkpoint.py
nobrainer/processing/generation.py
nobrainer/processing/segmentation.py
nobrainer/tests/__init__.py
nobrainer/tests/checkpoint_test.py
nobrainer/tests/dataset_test.py
nobrainer/tests/io_test.py
nobrainer/tests/losses_test.py
nobrainer/tests/metrics_test.py
nobrainer/tests/prediction_test.py
nobrainer/tests/test_intensity_transforms.py
nobrainer/tests/test_spatial_transforms.py
nobrainer/tests/test_utils.py
nobrainer-1.2.1.dist-info/LICENSE
nobrainer-1.2.1.dist-info/METADATA
nobrainer-1.2.1.dist-info/WHEEL
nobrainer-1.2.1.dist-info/entry_points.txt
nobrainer-1.2.1.dist-info/top_level.txt
nobrainer-1.2.1.dist-info/RECORD
