Metadata-Version: 2.1
Name: nobrainer
Version: 1.2.1
Summary: A framework for developing neural network models for 3D image processing.
Home-page: https://neuronets.github.io
Author: Nobrainer Developers
Author-email: jakub.kaczmarzyk@gmail.com
License: Apache License, 2.0
Project-URL: Source Code, https://github.com/neuronets/nobrainer
Classifier: Development Status :: 3 - Alpha
Classifier: Environment :: Console
Classifier: Intended Audience :: Developers
Classifier: Intended Audience :: Education
Classifier: Intended Audience :: Healthcare Industry
Classifier: Intended Audience :: Science/Research
Classifier: License :: OSI Approved :: Apache Software License
Classifier: Operating System :: OS Independent
Classifier: Programming Language :: Python :: 3
Classifier: Programming Language :: Python :: 3 :: Only
Classifier: Programming Language :: Python :: 3.9
Classifier: Programming Language :: Python :: 3.10
Classifier: Programming Language :: Python :: 3.11
Classifier: Programming Language :: Python :: 3.12
Classifier: Topic :: Scientific/Engineering :: Artificial Intelligence
Classifier: Topic :: Software Development
Classifier: Topic :: Software Development :: Libraries :: Python Modules
Requires-Python: >=3.9
License-File: LICENSE
Requires-Dist: click
Requires-Dist: fsspec
Requires-Dist: joblib
Requires-Dist: nibabel
Requires-Dist: numpy
Requires-Dist: scikit-image
Requires-Dist: tensorflow-probability <0.24
Requires-Dist: tensorflow <2.16,>=2.13
Requires-Dist: tensorflow-addons ~=0.23.0
Requires-Dist: psutil
Provides-Extra: and-cuda
Requires-Dist: tensorflow[and-cuda] <2.16,>=2.13 ; extra == 'and-cuda'
Provides-Extra: dev
Requires-Dist: pre-commit ; extra == 'dev'
Requires-Dist: pytest ; extra == 'dev'
Requires-Dist: pytest-cov ; extra == 'dev'
Requires-Dist: scipy ; extra == 'dev'
